Tmlog/__init__.py
Tmlog-1.0.2.dist-info/METADATA
Tmlog-1.0.2.dist-info/WHEEL
Tmlog-1.0.2.dist-info/top_level.txt
Tmlog-1.0.2.dist-info/RECORD
