Metadata-Version: 2.1
Name: Tmlog
Version: 1.0.2
Summary: Time logger
Home-page: https://github.com/gudwns1215/Tmlog
Author: moon1215
Author-email: gudwns1215@gmail.com
License: MIT
Platform: UNKNOWN
Requires-Python: >=3
